flexparser/__init__.py
flexparser/flexparser.py
flexparser/py.typed
flexparser/testsuite/__init__.py
flexparser/testsuite/bla1.txt
flexparser/testsuite/bla2.txt
flexparser/testsuite/common.py
flexparser/testsuite/test_element_block.py
flexparser/testsuite/test_iterators.py
flexparser/testsuite/test_parser.py
flexparser/testsuite/test_project.py
flexparser/testsuite/test_util.py
flexparser-0.3.1.dist-info/AUTHORS
flexparser-0.3.1.dist-info/LICENSE
flexparser-0.3.1.dist-info/METADATA
flexparser-0.3.1.dist-info/WHEEL
flexparser-0.3.1.dist-info/top_level.txt
flexparser-0.3.1.dist-info/RECORD
