Metadata-Version: 2.1
Name: flexparser
Version: 0.3.1
Summary: Parsing made fun ... using typing.
Author-email: "Hernan E. Grecco" <hernan.grecco@gmail.com>
Maintainer-email: "Hernan E. Grecco" <hernan.grecco@gmail.com>
License: BSD-3-Clause
Project-URL: Homepage, https://github.com/hgrecco/flexparser
Keywords: parser,code,parsing,source
Classifier: Development Status :: 4 - Beta
Classifier: Intended Audience :: Developers
Classifier: Intended Audience :: Science/Research
Classifier: License :: OSI Approved :: BSD License
Classifier: Operating System :: MacOS :: MacOS X
Classifier: Operating System :: Microsoft :: Windows
Classifier: Operating System :: POSIX
Classifier: Programming Language :: Python
Classifier: Topic :: System :: Filesystems
Classifier: Topic :: Software Development :: Libraries
Classifier: Topic :: Utilities
Classifier: Programming Language :: Python :: 3.9
Classifier: Programming Language :: Python :: 3.10
Classifier: Programming Language :: Python :: 3.11
Classifier: Programming Language :: Python :: 3.12
Requires-Python: >=3.9
License-File: LICENSE
License-File: AUTHORS
Requires-Dist: typing_extensions
Provides-Extra: test
Requires-Dist: pytest; extra == "test"
Requires-Dist: pytest-mpl; extra == "test"
Requires-Dist: pytest-cov; extra == "test"
Requires-Dist: pytest-subtests; extra == "test"
